README
setup.py
hkp/__init__.py
hkp/client.py
hkp/tests.py
hkp/utils.py
python_hkp.egg-info/PKG-INFO
python_hkp.egg-info/SOURCES.txt
python_hkp.egg-info/dependency_links.txt
python_hkp.egg-info/top_level.txt