Metadata-Version: 1.0
Name: python-hkp
Version: 0.1.3
Summary: Python HKP client
Home-page: https://github.com/dgladkov/python-hkp/
Author: Dmitry Gladkov
Author-email: dmitry.gladkov@gmail.com
License: BSD
Platform: any
Classifier: Development Status :: 4 - Beta
Classifier: Environment :: Console
Classifier: Intended Audience :: Developers
Classifier: License :: OSI Approved :: BSD License
Classifier: Operating System :: OS Independent
Classifier: Programming Language :: Python
Classifier: Topic :: Software Development :: Libraries :: Python Modules
